pinjected_openai/__init__.py
pinjected_openai/clients.py
pinjected_openai/compatibles.py
pinjected_openai/vision_llm.py
pinjected_openai/whisper.py
pinjected_openai/openrouter/__init__.py
pinjected_openai/openrouter/util.py
pinjected_openai-0.4.26.dist-info/METADATA
pinjected_openai-0.4.26.dist-info/WHEEL
pinjected_openai-0.4.26.dist-info/RECORD
