Metadata-Version: 2.3
Name: pinjected-openai
Version: 0.4.26
Summary: openai bindings for pinjected library
Author-email: proboscis <nameissoap@gmail.com>
License: MIT
Classifier: License :: OSI Approved :: MIT License
Classifier: Operating System :: OS Independent
Classifier: Programming Language :: Python :: 3
Requires-Python: >=3.10
Requires-Dist: filelock
Requires-Dist: injected-utils
Requires-Dist: loguru
Requires-Dist: moviepy>=1.0.3
Requires-Dist: openai>=1.61.0
Requires-Dist: pandas
Requires-Dist: pillow
Requires-Dist: pinjected
Requires-Dist: pinjected-rate-limit>=0.1.0
Requires-Dist: pydub
Requires-Dist: reactivex>=4.0.4
Requires-Dist: tenacity>=9.0.0
Requires-Dist: tiktoken
